tests/__init__.py
tests/test_character.py
tests/test_client.py
theoneapi_sdk/__init__.py
theoneapi_sdk/client.py
theoneapi_sdk/enums.py
theoneapi_sdk/filter.py
theoneapi_sdk/request_handler.py
theoneapi_sdk/book/__init__.py
theoneapi_sdk/book/book.py
theoneapi_sdk/book/book_dataclass.py
theoneapi_sdk/chapter/__init__.py
theoneapi_sdk/chapter/chapter.py
theoneapi_sdk/chapter/chapter_dataclass.py
theoneapi_sdk/character/__init__.py
theoneapi_sdk/character/character.py
theoneapi_sdk/character/character_dataclass.py
theoneapi_sdk/movie/__init__.py
theoneapi_sdk/movie/movie.py
theoneapi_sdk/movie/movie_dataclass.py
theoneapi_sdk/quote/__init__.py
theoneapi_sdk/quote/quote.py
theoneapi_sdk/quote/quote_dataclass.py
lotr_eliram_sdk-1.0.2.dist-info/LICENSE
lotr_eliram_sdk-1.0.2.dist-info/METADATA
lotr_eliram_sdk-1.0.2.dist-info/WHEEL
lotr_eliram_sdk-1.0.2.dist-info/top_level.txt
lotr_eliram_sdk-1.0.2.dist-info/RECORD
